pyopensim/__init__.py
pyopensim/_actuators.so
pyopensim/_analyses.so
pyopensim/_common.so
pyopensim/_simbody.so
pyopensim/_simulation.so
pyopensim/_tools.so
pyopensim/_version.py
pyopensim/actuators.py
pyopensim/analyses.py
pyopensim/common.py
pyopensim/py.typed
pyopensim/simbody.py
pyopensim/simulation.py
pyopensim/tools.py
pyopensim/lib/libSimTKcommon.so
pyopensim/lib/libSimTKcommon.so.3.8
pyopensim/lib/libSimTKmath.so
pyopensim/lib/libSimTKmath.so.3.8
pyopensim/lib/libSimTKsimbody.so
pyopensim/lib/libSimTKsimbody.so.3.8
pyopensim/lib/libosimActuators.so
pyopensim/lib/libosimAnalyses.so
pyopensim/lib/libosimCommon.so
pyopensim/lib/libosimLepton.so
pyopensim/lib/libosimSimulation.so
pyopensim/lib/libosimTools.so
pyopensim/lib/libosimdocopt.so
pyopensim/pyopensim/version.py
pyopensim.libs/libezc3d-87cbf7b9.so
pyopensim-4.5.2.0.dist-info/METADATA
pyopensim-4.5.2.0.dist-info/WHEEL
pyopensim-4.5.2.0.dist-info/RECORD
pyopensim-4.5.2.0.dist-info/licenses/LICENSE
