Metadata-Version: 2.2
Name: pyopensim
Version: 4.5.2.0
Summary: PyOpenSim: Portable Python bindings for OpenSim
Author-Email: Senthur Ayyappan <senthurayyappan@umich.edu>
Classifier: Programming Language :: Python :: 3 :: Only
Classifier: Programming Language :: Python :: 3.10
Classifier: Programming Language :: Python :: 3.11
Classifier: Programming Language :: Python :: 3.12
Classifier: Topic :: Scientific/Engineering
Classifier: Topic :: Scientific/Engineering :: Physics
Requires-Python: >=3.10
Requires-Dist: numpy
Provides-Extra: test
Requires-Dist: pytest; extra == "test"
Provides-Extra: build
Requires-Dist: cibuildwheel; extra == "build"
